{"results": [{"time": "All Day", "unixtime": 1656547200.0, "impact": "low", "currency": "GE", "event": "Prelim CPI m/m", "forecast": "0.4%", "source": "ForexFactory/MetalsMine"}, {"time": "3:00am", "unixtime": 1656572400.0, "impact": "low", "currency": "SP", "event": "Flash CPI y/y", "forecast": "8.8%", "source": "ForexFactory/MetalsMine"}, {"time": "4:00am", "unixtime": 1656576000.0, "impact": "low", "currency": "EZ", "event": "M3 Money Supply y/y", "forecast": "5.8%", "source": "ForexFactory/MetalsMine"}, {"time": "4:00am", "unixtime": 1656576000.0, "impact": "medium", "currency": "UK", "event": "LME Copper Inventories", "forecast": "failed", "source": "ForexFactory/MetalsMine"}, {"time": "8:30am", "unixtime": 1656592200.0, "impact": "medium", "currency": "US", "event": "Final GDP q/q", "forecast": "-1.5%", "source": "ForexFactory/MetalsMine"}, {"time": "8:30am", "unixtime": 1656592200.0, "impact": "low", "currency": "US", "event": "Final GDP Price Index q/q", "forecast": "8.1%", "source": "ForexFactory/MetalsMine"}, {"time": "9:00am", "unixtime": 1656594000.0, "impact": "low", "currency": "EZ", "event": "ECB President Lagarde Speaks", "forecast": "failed", "source": "ForexFactory/MetalsMine"}, {"time": "9:00am", "unixtime": 1656594000.0, "impact": "low", "currency": "UK", "event": "BOE Gov Bailey Speaks", "forecast": "failed", "source": "ForexFactory/MetalsMine"}, {"time": "9:00am", "unixtime": 1656594000.0, "impact": "high", "currency": "US", "event": "Fed Chair Powell Speaks", "forecast": "failed", "source": "ForexFactory/MetalsMine"}, {"time": "11:00am", "unixtime": 1656601200.0, "impact": "low", "currency": "EZ", "event": "ECB President Lagarde Speaks", "forecast": "failed", "source": "ForexFactory/MetalsMine"}, {"time": "12:00pm", "unixtime": 1656604800.0, "impact": "low", "currency": "RU", "event": "Industrial Production y/y", "forecast": "-3.0%", "source": "ForexFactory/MetalsMine"}, {"time": "12:00pm", "unixtime": 1656604800.0, "impact": "low", "currency": "RU", "event": "Unemployment Rate", "forecast": "4.2%", "source": "ForexFactory/MetalsMine"}, {"time": "7:50pm", "unixtime": 1656633000.0, "impact": "low", "currency": "JN", "event": "Prelim Industrial Production m/m", "forecast": "-0.2%", "source": "ForexFactory/MetalsMine"}, {"time": "9:30pm", "unixtime": 1656639000.0, "impact": "low", "currency": "CH", "event": "Manufacturing PMI", "forecast": "50.6", "source": "ForexFactory/MetalsMine"}, {"time": "9:32pm", "unixtime": 1656639120.0, "impact": "low", "currency": "CH", "event": "Non-Manufacturing PMI", "forecast": "50.4", "source": "ForexFactory/MetalsMine"}]}