{"resultz": [{"time": "2022-06-12 22:45:00", "unixtime": 1655073900.0, "country": "NZD", "impact": "low", "event": "External Migration & Visitors (Apr)", "forecast": ""}, {"time": "2022-06-12 22:45:00", "unixtime": 1655073900.0, "country": "NZD", "impact": "low", "event": "Permanent/Long-Term Migration (Apr)", "forecast": ""}, {"time": "2022-06-12 23:50:00", "unixtime": 1655077800.0, "country": "JPY", "impact": "medium", "event": "BSI Large Manufacturing Conditions (Q2)", "forecast": ""}, {"time": "2022-06-13 06:00:00", "unixtime": 1655100000.0, "country": "GBP", "impact": "low", "event": "U.K. Construction Output (YoY) (Apr)", "forecast": "3.8%"}, {"time": "2022-06-13 06:00:00", "unixtime": 1655100000.0, "country": "GBP", "impact": "low", "event": "Construction Output (MoM) (Apr)", "forecast": "-0.5%"}, {"time": "2022-06-13 06:00:00", "unixtime": 1655100000.0, "country": "GBP", "impact": "high", "event": "GDP (MoM)", "forecast": "0.1%"}, {"time": "2022-06-13 06:00:00", "unixtime": 1655100000.0, "country": "GBP", "impact": "high", "event": "GDP (QoQ)", "forecast": "0.4%"}, {"time": "2022-06-13 06:00:00", "unixtime": 1655100000.0, "country": "GBP", "impact": "high", "event": "GDP (YoY)", "forecast": "3.9%"}, {"time": "2022-06-13 06:00:00", "unixtime": 1655100000.0, "country": "GBP", "impact": "low", "event": "Index of Services", "forecast": "0.1%"}, {"time": "2022-06-13 06:00:00", "unixtime": 1655100000.0, "country": "GBP", "impact": "low", "event": "Industrial Production (YoY) (Apr)", "forecast": "1.7%"}, {"time": "2022-06-13 06:00:00", "unixtime": 1655100000.0, "country": "GBP", "impact": "medium", "event": "Industrial Production (MoM) (Apr)", "forecast": "0.2%"}, {"time": "2022-06-13 06:00:00", "unixtime": 1655100000.0, "country": "GBP", "impact": "high", "event": "Manufacturing Production (MoM) (Apr)", "forecast": "0.2%"}, {"time": "2022-06-13 06:00:00", "unixtime": 1655100000.0, "country": "GBP", "impact": "low", "event": "Manufacturing Production (YoY) (Apr)", "forecast": "1.8%"}, {"time": "2022-06-13 06:00:00", "unixtime": 1655100000.0, "country": "GBP", "impact": "high", "event": "Monthly GDP 3M/3M Change", "forecast": "0.4%"}, {"time": "2022-06-13 06:00:00", "unixtime": 1655100000.0, "country": "GBP", "impact": "medium", "event": "Trade Balance (Apr)", "forecast": "-22.50B"}, {"time": "2022-06-13 06:00:00", "unixtime": 1655100000.0, "country": "GBP", "impact": "medium", "event": "Trade Balance Non-EU (Apr)", "forecast": ""}, {"time": "2022-06-13 08:00:00", "unixtime": 1655107200.0, "country": "EUR", "impact": "low", "event": "Italian Quarterly Unemployment Rate", "forecast": ""}, {"time": "2022-06-13 11:00:00", "unixtime": 1655118000.0, "country": "GBP", "impact": "medium", "event": "NIESR GDP Estimate", "forecast": ""}, {"time": "2022-06-13 11:00:00", "unixtime": 1655118000.0, "country": "EUR", "impact": "low", "event": "Spanish Consumer Confidence", "forecast": ""}, {"time": "2022-06-13 11:25:00", "unixtime": 1655119500.0, "country": "BRL", "impact": "medium", "event": "BCB Focus Market Readout", "forecast": ""}, {"time": "2022-06-13 12:00:00", "unixtime": 1655121600.0, "country": "INR", "impact": "medium", "event": "CPI (YoY) (May)", "forecast": "7.10%"}, {"time": "2022-06-13 13:00:00", "unixtime": 1655125200.0, "country": "EUR", "impact": "low", "event": "French 12-Month BTF Auction", "forecast": ""}, {"time": "2022-06-13 13:00:00", "unixtime": 1655125200.0, "country": "EUR", "impact": "low", "event": "French 3-Month BTF Auction", "forecast": ""}, {"time": "2022-06-13 13:00:00", "unixtime": 1655125200.0, "country": "EUR", "impact": "low", "event": "French 6-Month BTF Auction", "forecast": ""}, {"time": "2022-06-13 15:30:00", "unixtime": 1655134200.0, "country": "USD", "impact": "low", "event": "3-Month Bill Auction", "forecast": ""}, {"time": "2022-06-13 15:30:00", "unixtime": 1655134200.0, "country": "USD", "impact": "low", "event": "6-Month Bill Auction", "forecast": ""}, {"time": "2022-06-13 18:00:00", "unixtime": 1655143200.0, "country": "USD", "impact": "medium", "event": "FOMC Member Brainard Speaks", "forecast": ""}, {"time": "2022-06-13 18:00:00", "unixtime": 1655143200.0, "country": "BRL", "impact": "low", "event": "Trade Balance (May)", "forecast": "4.57B"}, {"time": "2022-06-13 22:45:00", "unixtime": 1655160300.0, "country": "NZD", "impact": "low", "event": "FPI (MoM) (May)", "forecast": ""}, {"time": "2022-06-14 01:00:00", "unixtime": 1655168400.0, "country": "KRW", "impact": "medium", "event": "BOK Financial Stability Board Meeting Minutes", "forecast": ""}, {"time": "2022-06-14 01:30:00", "unixtime": 1655170200.0, "country": "AUD", "impact": "medium", "event": "NAB Business Confidence (May)", "forecast": ""}, {"time": "2022-06-14 01:30:00", "unixtime": 1655170200.0, "country": "AUD", "impact": "low", "event": "NAB Business Survey (May)", "forecast": ""}, {"time": "2022-06-14 03:12:00", "unixtime": 1655176320.0, "country": "CNY", "impact": "low", "event": "FDI (May)", "forecast": ""}, {"time": "2022-06-14 04:00:00", "unixtime": 1655179200.0, "country": "IDR", "impact": "low", "event": "Car Sales (YoY) (May)", "forecast": ""}, {"time": "2022-06-14 04:30:00", "unixtime": 1655181000.0, "country": "JPY", "impact": "low", "event": "Capacity Utilization (MoM) (Apr)", "forecast": ""}, {"time": "2022-06-14 04:30:00", "unixtime": 1655181000.0, "country": "JPY", "impact": "medium", "event": "Industrial Production (MoM) (Apr)", "forecast": ""}, {"time": "2022-06-14 06:00:00", "unixtime": 1655186400.0, "country": "GBP", "impact": "low", "event": "Average Earnings ex Bonus (Apr)", "forecast": "4.0%"}, {"time": "2022-06-14 06:00:00", "unixtime": 1655186400.0, "country": "GBP", "impact": "high", "event": "Average Earnings Index +Bonus (Apr)", "forecast": "7.6%"}, {"time": "2022-06-14 06:00:00", "unixtime": 1655186400.0, "country": "GBP", "impact": "high", "event": "Claimant Count Change (May)", "forecast": "-49.4K"}, {"time": "2022-06-14 06:00:00", "unixtime": 1655186400.0, "country": "GBP", "impact": "medium", "event": "Employment Change 3M/3M (MoM) (Apr)", "forecast": "105K"}, {"time": "2022-06-14 06:00:00", "unixtime": 1655186400.0, "country": "GBP", "impact": "medium", "event": "Unemployment Rate (Apr)", "forecast": "3.6%"}, {"time": "2022-06-14 06:00:00", "unixtime": 1655186400.0, "country": "EUR", "impact": "medium", "event": "German CPI (MoM) (May)", "forecast": "0.0%"}, {"time": "2022-06-14 06:00:00", "unixtime": 1655186400.0, "country": "EUR", "impact": "low", "event": "German CPI (YoY) (May)", "forecast": "7.9%"}, {"time": "2022-06-14 06:00:00", "unixtime": 1655186400.0, "country": "EUR", "impact": "low", "event": "German HICP (YoY) (May)", "forecast": "8.7%"}, {"time": "2022-06-14 06:00:00", "unixtime": 1655186400.0, "country": "EUR", "impact": "low", "event": "German HICP (MoM) (May)", "forecast": "1.1%"}, {"time": "2022-06-14 06:00:00", "unixtime": 1655186400.0, "country": "EUR", "impact": "low", "event": "German WPI (YoY) (May)", "forecast": ""}, {"time": "2022-06-14 06:00:00", "unixtime": 1655186400.0, "country": "EUR", "impact": "low", "event": "German WPI (MoM) (May)", "forecast": ""}, {"time": "2022-06-14 06:30:00", "unixtime": 1655188200.0, "country": "INR", "impact": "low", "event": "WPI Food (YoY) (May)", "forecast": ""}, {"time": "2022-06-14 06:30:00", "unixtime": 1655188200.0, "country": "INR", "impact": "low", "event": "WPI Fuel (YoY) (May)", "forecast": ""}, {"time": "2022-06-14 06:30:00", "unixtime": 1655188200.0, "country": "INR", "impact": "medium", "event": "WPI Inflation (YoY) (May)", "forecast": "15.10%"}, {"time": "2022-06-14 06:30:00", "unixtime": 1655188200.0, "country": "INR", "impact": "low", "event": "WPI Manufacturing Inflation (YoY) (May)", "forecast": ""}, {"time": "2022-06-14 07:00:00", "unixtime": 1655190000.0, "country": "EUR", "impact": "medium", "event": "German Buba Mauderer Speaks", "forecast": ""}, {"time": "2022-06-14 08:00:00", "unixtime": 1655193600.0, "country": "NOK", "impact": "low", "event": "Norges Bank regional network Survey", "forecast": ""}, {"time": "2022-06-14 08:40:00", "unixtime": 1655196000.0, "country": "EUR", "impact": "low", "event": "Spanish 3-Month Letras Auction", "forecast": ""}, {"time": "2022-06-14 09:00:00", "unixtime": 1655197200.0, "country": "EUR", "impact": "medium", "event": "German ZEW Current Conditions (Jun)", "forecast": "-31.0"}, {"time": "2022-06-14 09:00:00", "unixtime": 1655197200.0, "country": "EUR", "impact": "high", "event": "German ZEW Economic Sentiment (Jun)", "forecast": "-27.5"}, {"time": "2022-06-14 09:00:00", "unixtime": 1655197200.0, "country": "EUR", "impact": "medium", "event": "ZEW Economic Sentiment (Jun)", "forecast": ""}, {"time": "2022-06-14 09:00:00", "unixtime": 1655197200.0, "country": "ZAR", "impact": "low", "event": "Business Confidence (Apr)", "forecast": ""}, {"time": "2022-06-14 09:05:00", "unixtime": 1655197500.0, "country": "ZAR", "impact": "low", "event": "Business Confidence", "forecast": ""}, {"time": "2022-06-14 09:30:00", "unixtime": 1655199000.0, "country": "EUR", "impact": "low", "event": "Italian 3-Year BTP Auction", "forecast": ""}, {"time": "2022-06-14 09:30:00", "unixtime": 1655199000.0, "country": "EUR", "impact": "low", "event": "Italian 30-Year BTP Auction", "forecast": ""}, {"time": "2022-06-14 09:30:00", "unixtime": 1655199000.0, "country": "EUR", "impact": "low", "event": "Italian 7-Year BTP Auction", "forecast": ""}, {"time": "2022-06-14 10:00:00", "unixtime": 1655200800.0, "country": "USD", "impact": "low", "event": "NFIB Small Business Optimism (May)", "forecast": ""}, {"time": "2022-06-14 10:30:00", "unixtime": 1655202600.0, "country": "EUR", "impact": "low", "event": "German 2-Year Schatz Auction", "forecast": ""}, {"time": "2022-06-14 11:00:00", "unixtime": 1655204400.0, "country": "USD", "impact": "medium", "event": "OPEC Monthly Report", "forecast": ""}, {"time": "2022-06-14 11:15:00", "unixtime": 1655205300.0, "country": "EUR", "impact": "medium", "event": "ECB Supervisory Board Member Tuominen Speaks", "forecast": ""}, {"time": "2022-06-14 12:00:00", "unixtime": 1655208000.0, "country": "BRL", "impact": "low", "event": "Brazilian Service Sector Growth (MoM) (Apr)", "forecast": "0.4%"}, {"time": "2022-06-14 12:00:00", "unixtime": 1655208000.0, "country": "BRL", "impact": "low", "event": "Brazilian Service Sector Growth (YoY) (Apr)", "forecast": "10.4%"}, {"time": "2022-06-14 12:30:00", "unixtime": 1655209800.0, "country": "USD", "impact": "medium", "event": "Core PPI (MoM) (May)", "forecast": "0.6%"}, {"time": "2022-06-14 12:30:00", "unixtime": 1655209800.0, "country": "USD", "impact": "low", "event": "Core PPI (YoY) (May)", "forecast": "8.6%"}, {"time": "2022-06-14 12:30:00", "unixtime": 1655209800.0, "country": "USD", "impact": "high", "event": "PPI (MoM) (May)", "forecast": "0.8%"}, {"time": "2022-06-14 12:30:00", "unixtime": 1655209800.0, "country": "USD", "impact": "low", "event": "PPI (YoY) (May)", "forecast": "10.9%"}, {"time": "2022-06-14 12:30:00", "unixtime": 1655209800.0, "country": "CAD", "impact": "medium", "event": "Manufacturing Sales (MoM) (Apr)", "forecast": "1.6%"}, {"time": "2022-06-14 12:30:00", "unixtime": 1655209800.0, "country": "CAD", "impact": "low", "event": "New Motor Vehicle Sales (MoM)", "forecast": ""}, {"time": "2022-06-14 12:55:00", "unixtime": 1655211300.0, "country": "USD", "impact": "low", "event": "Redbook (YoY)", "forecast": ""}, {"time": "2022-06-14 14:00:00", "unixtime": 1655215200.0, "country": "USD", "impact": "low", "event": "IBD/TIPP Economic Optimism", "forecast": ""}, {"time": "2022-06-14 14:45:00", "unixtime": 1655217900.0, "country": "EUR", "impact": "medium", "event": "ECB McCaul Speaks", "forecast": ""}, {"time": "2022-06-14 15:30:00", "unixtime": 1655220600.0, "country": "USD", "impact": "low", "event": "52-Week Bill Auction", "forecast": ""}, {"time": "2022-06-14 17:00:00", "unixtime": 1655226000.0, "country": "EUR", "impact": "medium", "event": "ECB's Schnabel Speaks", "forecast": ""}, {"time": "2022-06-14 20:30:00", "unixtime": 1655238600.0, "country": "USD", "impact": "medium", "event": "API Weekly Crude Oil Stock", "forecast": "-1.200M"}, {"time": "2022-06-14 22:45:00", "unixtime": 1655246700.0, "country": "NZD", "impact": "medium", "event": "Current Account (QoQ) (Q1)", "forecast": "-5.50B"}, {"time": "2022-06-14 22:45:00", "unixtime": 1655246700.0, "country": "NZD", "impact": "medium", "event": "Current Account (YoY) (Q1)", "forecast": "-22.50B"}, {"time": "2022-06-14 22:45:00", "unixtime": 1655246700.0, "country": "NZD", "impact": "low", "event": "Current Account % of GDP (Q1)", "forecast": "-6.30%"}, {"time": "2022-06-14 23:00:00", "unixtime": 1655247600.0, "country": "KRW", "impact": "low", "event": "Unemployment Rate (May)", "forecast": ""}, {"time": "2022-06-14 23:00:00", "unixtime": 1655247600.0, "country": "JPY", "impact": "low", "event": "Reuters Tankan Index (Jun)", "forecast": ""}, {"time": "2022-06-14 23:50:00", "unixtime": 1655250600.0, "country": "JPY", "impact": "low", "event": "Core Machinery Orders (YoY) (Apr)", "forecast": "5.3%"}, {"time": "2022-06-14 23:50:00", "unixtime": 1655250600.0, "country": "JPY", "impact": "low", "event": "Core Machinery Orders (MoM) (Apr)", "forecast": "-1.5%"}, {"time": "2022-06-14 23:55:00", "unixtime": 1655250900.0, "country": "KRW", "impact": "low", "event": "Exports (YoY) (May)", "forecast": ""}, {"time": "2022-06-14 23:55:00", "unixtime": 1655250900.0, "country": "KRW", "impact": "low", "event": "Imports (YoY) (May)", "forecast": ""}, {"time": "2022-06-14 23:55:00", "unixtime": 1655250900.0, "country": "KRW", "impact": "low", "event": "Trade Balance (May)", "forecast": ""}, {"time": "2022-06-15 00:30:00", "unixtime": 1655253000.0, "country": "AUD", "impact": "medium", "event": "Westpac Consumer Sentiment (Jun)", "forecast": ""}, {"time": "2022-06-15 02:00:00", "unixtime": 1655258400.0, "country": "CNY", "impact": "medium", "event": "Fixed Asset Investment (YoY) (May)", "forecast": "6.0%"}, {"time": "2022-06-15 02:00:00", "unixtime": 1655258400.0, "country": "CNY", "impact": "high", "event": "Industrial Production (YoY) (May)", "forecast": "-0.7%"}, {"time": "2022-06-15 02:00:00", "unixtime": 1655258400.0, "country": "CNY", "impact": "medium", "event": "Chinese Industrial Production YTD  (YoY) (May)", "forecast": ""}, {"time": "2022-06-15 02:00:00", "unixtime": 1655258400.0, "country": "CNY", "impact": "low", "event": "Retail Sales (YoY) (May)", "forecast": "-7.1%"}, {"time": "2022-06-15 02:00:00", "unixtime": 1655258400.0, "country": "CNY", "impact": "low", "event": "Chinese Retail Sales YTD  (YoY) (May)", "forecast": ""}, {"time": "2022-06-15 02:00:00", "unixtime": 1655258400.0, "country": "CNY", "impact": "medium", "event": "Chinese Unemployment Rate", "forecast": "6.1%"}, {"time": "2022-06-15 02:00:00", "unixtime": 1655258400.0, "country": "CNY", "impact": "medium", "event": "NBS Press Conference", "forecast": ""}, {"time": "2022-06-15 03:00:00", "unixtime": 1655262000.0, "country": "KRW", "impact": "low", "event": "M2 Money supply (Apr)", "forecast": ""}, {"time": "2022-06-15 04:00:00", "unixtime": 1655265600.0, "country": "IDR", "impact": "low", "event": "Export Growth (YoY) (May)", "forecast": "38.69%"}, {"time": "2022-06-15 04:00:00", "unixtime": 1655265600.0, "country": "IDR", "impact": "low", "event": "Import Growth (YoY) (May)", "forecast": "32.80%"}, {"time": "2022-06-15 04:00:00", "unixtime": 1655265600.0, "country": "IDR", "impact": "medium", "event": "Trade Balance (May)", "forecast": "3.83B"}, {"time": "2022-06-15 04:30:00", "unixtime": 1655267400.0, "country": "JPY", "impact": "medium", "event": "Tertiary Industry Activity Index (MoM)", "forecast": ""}, {"time": "2022-06-15 06:00:00", "unixtime": 1655272800.0, "country": "CHF", "impact": "low", "event": "SECO Economic Forecasts", "forecast": ""}, {"time": "2022-06-15 06:00:00", "unixtime": 1655272800.0, "country": "EUR", "impact": "low", "event": "German WPI (YoY) (May)", "forecast": ""}, {"time": "2022-06-15 06:00:00", "unixtime": 1655272800.0, "country": "EUR", "impact": "low", "event": "German WPI (MoM) (May)", "forecast": ""}, {"time": "2022-06-15 06:00:00", "unixtime": 1655272800.0, "country": "NOK", "impact": "low", "event": "Trade Balance (May)", "forecast": ""}, {"time": "2022-06-15 06:30:00", "unixtime": 1655274600.0, "country": "CHF", "impact": "medium", "event": "PPI (MoM) (May)", "forecast": ""}, {"time": "2022-06-15 06:30:00", "unixtime": 1655274600.0, "country": "CHF", "impact": "low", "event": "PPI (YoY) (May)", "forecast": ""}, {"time": "2022-06-15 06:45:00", "unixtime": 1655275500.0, "country": "EUR", "impact": "medium", "event": "French CPI (MoM) (May)", "forecast": "0.6%"}, {"time": "2022-06-15 06:45:00", "unixtime": 1655275500.0, "country": "EUR", "impact": "low", "event": "French CPI (YoY)", "forecast": "5.2%"}, {"time": "2022-06-15 06:45:00", "unixtime": 1655275500.0, "country": "EUR", "impact": "medium", "event": "French HICP (MoM) (May)", "forecast": "0.7%"}, {"time": "2022-06-15 06:45:00", "unixtime": 1655275500.0, "country": "EUR", "impact": "low", "event": "French HICP (YoY) (May)", "forecast": "5.8%"}, {"time": "2022-06-15 08:00:00", "unixtime": 1655280000.0, "country": "USD", "impact": "medium", "event": "IEA Monthly Report", "forecast": ""}, {"time": "2022-06-15 09:00:00", "unixtime": 1655283600.0, "country": "EUR", "impact": "low", "event": "Industrial Production (YoY) (Apr)", "forecast": "-1.1%"}, {"time": "2022-06-15 09:00:00", "unixtime": 1655283600.0, "country": "EUR", "impact": "medium", "event": "Industrial Production (MoM) (Apr)", "forecast": "-2.0%"}, {"time": "2022-06-15 09:00:00", "unixtime": 1655283600.0, "country": "EUR", "impact": "medium", "event": "Trade Balance (Apr)", "forecast": ""}, {"time": "2022-06-15 09:15:00", "unixtime": 1655284500.0, "country": "EUR", "impact": "medium", "event": "German Buba President Nagel Speaks", "forecast": ""}, {"time": "2022-06-15 11:00:00", "unixtime": 1655290800.0, "country": "USD", "impact": "low", "event": "MBA 30-Year Mortgage Rate", "forecast": ""}, {"time": "2022-06-15 11:00:00", "unixtime": 1655290800.0, "country": "USD", "impact": "low", "event": "MBA Mortgage Applications (WoW)", "forecast": ""}, {"time": "2022-06-15 11:00:00", "unixtime": 1655290800.0, "country": "USD", "impact": "low", "event": "MBA Purchase Index", "forecast": ""}, {"time": "2022-06-15 11:00:00", "unixtime": 1655290800.0, "country": "USD", "impact": "low", "event": "Mortgage Market Index", "forecast": ""}, {"time": "2022-06-15 11:00:00", "unixtime": 1655290800.0, "country": "USD", "impact": "low", "event": "Mortgage Refinance Index", "forecast": ""}, {"time": "2022-06-15 11:00:00", "unixtime": 1655290800.0, "country": "BRL", "impact": "medium", "event": "IGP-10 Inflation Index (MoM) (Jun)", "forecast": "0.6%"}, {"time": "2022-06-15 11:00:00", "unixtime": 1655290800.0, "country": "ZAR", "impact": "low", "event": "Retail Sales (YoY) (Apr)", "forecast": "1.6%"}, {"time": "2022-06-15 11:30:00", "unixtime": 1655292600.0, "country": "INR", "impact": "low", "event": "Exports (USD) (May)", "forecast": ""}, {"time": "2022-06-15 11:30:00", "unixtime": 1655292600.0, "country": "INR", "impact": "low", "event": "Imports (USD) (May)", "forecast": ""}, {"time": "2022-06-15 11:30:00", "unixtime": 1655292600.0, "country": "INR", "impact": "low", "event": "M3 Money Supply", "forecast": ""}, {"time": "2022-06-15 11:30:00", "unixtime": 1655292600.0, "country": "INR", "impact": "low", "event": "Trade Balance (May)", "forecast": "-23.20B"}, {"time": "2022-06-15 12:00:00", "unixtime": 1655294400.0, "country": "BRL", "impact": "low", "event": "IBC-Br Economic Activity (Mar)", "forecast": ""}, {"time": "2022-06-15 12:15:00", "unixtime": 1655295300.0, "country": "CAD", "impact": "medium", "event": "Housing Starts (May)", "forecast": "252.6K"}, {"time": "2022-06-15 12:30:00", "unixtime": 1655296200.0, "country": "USD", "impact": "high", "event": "Core Retail Sales (MoM) (May)", "forecast": "0.8%"}, {"time": "2022-06-15 12:30:00", "unixtime": 1655296200.0, "country": "USD", "impact": "medium", "event": "Export Price Index (MoM) (May)", "forecast": "1.3%"}, {"time": "2022-06-15 12:30:00", "unixtime": 1655296200.0, "country": "USD", "impact": "medium", "event": "Import Price Index (MoM) (May)", "forecast": "1.1%"}, {"time": "2022-06-15 12:30:00", "unixtime": 1655296200.0, "country": "USD", "impact": "medium", "event": "NY Empire State Manufacturing Index (Jun)", "forecast": "3.00"}, {"time": "2022-06-15 12:30:00", "unixtime": 1655296200.0, "country": "USD", "impact": "low", "event": "Retail Control (MoM) (May)", "forecast": "0.5%"}, {"time": "2022-06-15 12:30:00", "unixtime": 1655296200.0, "country": "USD", "impact": "high", "event": "Retail Sales (MoM) (May)", "forecast": "0.2%"}, {"time": "2022-06-15 12:30:00", "unixtime": 1655296200.0, "country": "USD", "impact": "low", "event": "Retail Sales (YoY) (May)", "forecast": ""}, {"time": "2022-06-15 12:30:00", "unixtime": 1655296200.0, "country": "USD", "impact": "low", "event": "Retail Sales Ex Gas/Autos (MoM) (May)", "forecast": ""}, {"time": "2022-06-15 12:55:00", "unixtime": 1655297700.0, "country": "USD", "impact": "low", "event": "Redbook (YoY)", "forecast": ""}, {"time": "2022-06-15 13:15:00", "unixtime": 1655298900.0, "country": "EUR", "impact": "medium", "event": "ECB's Panetta Speaks", "forecast": ""}, {"time": "2022-06-15 14:00:00", "unixtime": 1655301600.0, "country": "USD", "impact": "medium", "event": "Business Inventories (MoM) (Apr)", "forecast": "1.2%"}, {"time": "2022-06-15 14:00:00", "unixtime": 1655301600.0, "country": "USD", "impact": "low", "event": "NAHB Housing Market Index (Jun)", "forecast": "68"}, {"time": "2022-06-15 14:00:00", "unixtime": 1655301600.0, "country": "USD", "impact": "medium", "event": "Retail Inventories Ex Auto (Apr)", "forecast": ""}, {"time": "2022-06-15 14:30:00", "unixtime": 1655303400.0, "country": "USD", "impact": "high", "event": "Crude Oil Inventories", "forecast": "-1.314M"}, {"time": "2022-06-15 14:30:00", "unixtime": 1655303400.0, "country": "USD", "impact": "low", "event": "EIA Refinery Crude Runs  (WoW)", "forecast": ""}, {"time": "2022-06-15 14:30:00", "unixtime": 1655303400.0, "country": "USD", "impact": "low", "event": "Crude Oil Imports", "forecast": ""}, {"time": "2022-06-15 14:30:00", "unixtime": 1655303400.0, "country": "USD", "impact": "medium", "event": "Cushing Crude Oil Inventories", "forecast": ""}, {"time": "2022-06-15 14:30:00", "unixtime": 1655303400.0, "country": "USD", "impact": "low", "event": "Distillate Fuel Production", "forecast": ""}, {"time": "2022-06-15 14:30:00", "unixtime": 1655303400.0, "country": "USD", "impact": "low", "event": "EIA Weekly Distillates Stocks", "forecast": "0.292M"}, {"time": "2022-06-15 14:30:00", "unixtime": 1655303400.0, "country": "USD", "impact": "low", "event": "Gasoline Production", "forecast": ""}, {"time": "2022-06-15 14:30:00", "unixtime": 1655303400.0, "country": "USD", "impact": "low", "event": "Heating Oil Stockpiles", "forecast": ""}, {"time": "2022-06-15 14:30:00", "unixtime": 1655303400.0, "country": "USD", "impact": "low", "event": "EIA Weekly Refinery Utilization Rates (WoW)", "forecast": "0.5%"}, {"time": "2022-06-15 14:30:00", "unixtime": 1655303400.0, "country": "USD", "impact": "low", "event": "Gasoline Inventories", "forecast": "1.066M"}, {"time": "2022-06-15 16:20:00", "unixtime": 1655310000.0, "country": "EUR", "impact": "high", "event": "ECB President Lagarde Speaks", "forecast": ""}, {"time": "2022-06-15 18:00:00", "unixtime": 1655316000.0, "country": "USD", "impact": "medium", "event": "Interest Rate Projection - 1st Yr (Q2)", "forecast": ""}, {"time": "2022-06-15 18:00:00", "unixtime": 1655316000.0, "country": "USD", "impact": "medium", "event": "Interest Rate Projection - 2nd Yr (Q2)", "forecast": ""}, {"time": "2022-06-15 18:00:00", "unixtime": 1655316000.0, "country": "USD", "impact": "medium", "event": "Interest Rate Projection - Current (Q2)", "forecast": ""}, {"time": "2022-06-15 18:00:00", "unixtime": 1655316000.0, "country": "USD", "impact": "medium", "event": "Interest Rate Projection - Longer (Q2)", "forecast": ""}, {"time": "2022-06-15 18:00:00", "unixtime": 1655316000.0, "country": "USD", "impact": "high", "event": "FOMC Economic Projections", "forecast": ""}, {"time": "2022-06-15 18:00:00", "unixtime": 1655316000.0, "country": "USD", "impact": "high", "event": "FOMC Statement", "forecast": ""}, {"time": "2022-06-15 18:00:00", "unixtime": 1655316000.0, "country": "USD", "impact": "high", "event": "Fed Interest Rate Decision", "forecast": "1.50%"}, {"time": "2022-06-15 18:30:00", "unixtime": 1655317800.0, "country": "USD", "impact": "high", "event": "FOMC Press Conference", "forecast": ""}, {"time": "2022-06-15 20:00:00", "unixtime": 1655323200.0, "country": "USD", "impact": "low", "event": "US Foreign Buying, T-bonds (Apr)", "forecast": ""}, {"time": "2022-06-15 20:00:00", "unixtime": 1655323200.0, "country": "USD", "impact": "low", "event": "Overall Net Capital Flow (Apr)", "forecast": ""}, {"time": "2022-06-15 20:00:00", "unixtime": 1655323200.0, "country": "USD", "impact": "medium", "event": "TIC Net Long-Term Transactions (Apr)", "forecast": ""}, {"time": "2022-06-15 20:00:00", "unixtime": 1655323200.0, "country": "USD", "impact": "low", "event": "TIC Net Long-Term Transactions including Swaps (Apr)", "forecast": ""}, {"time": "2022-06-15 21:00:00", "unixtime": 1655326800.0, "country": "KRW", "impact": "low", "event": "Export Price Index (YoY) (May)", "forecast": ""}, {"time": "2022-06-15 21:00:00", "unixtime": 1655326800.0, "country": "KRW", "impact": "low", "event": "Import Price Index (YoY) (May)", "forecast": ""}, {"time": "2022-06-15 21:00:00", "unixtime": 1655326800.0, "country": "BRL", "impact": "medium", "event": "Interest Rate Decision", "forecast": "13.25%"}, {"time": "2022-06-15 22:45:00", "unixtime": 1655333100.0, "country": "NZD", "impact": "high", "event": "GDP (QoQ) (Q1)", "forecast": "0.6%"}, {"time": "2022-06-15 22:45:00", "unixtime": 1655333100.0, "country": "NZD", "impact": "low", "event": "GDP (YoY) (Q1)", "forecast": "3.3%"}, {"time": "2022-06-15 22:45:00", "unixtime": 1655333100.0, "country": "NZD", "impact": "low", "event": "GDP Annual Average (Q1)", "forecast": "5.3%"}, {"time": "2022-06-15 22:45:00", "unixtime": 1655333100.0, "country": "NZD", "impact": "low", "event": "GDP Expenditure (QoQ) (Q1)", "forecast": "0.8%"}, {"time": "2022-06-15 23:50:00", "unixtime": 1655337000.0, "country": "JPY", "impact": "medium", "event": "Adjusted Trade Balance", "forecast": ""}, {"time": "2022-06-15 23:50:00", "unixtime": 1655337000.0, "country": "JPY", "impact": "medium", "event": "Exports (YoY) (May)", "forecast": "16.4%"}, {"time": "2022-06-15 23:50:00", "unixtime": 1655337000.0, "country": "JPY", "impact": "low", "event": "Foreign Bonds Buying", "forecast": ""}, {"time": "2022-06-15 23:50:00", "unixtime": 1655337000.0, "country": "JPY", "impact": "low", "event": "Foreign Investments in Japanese Stocks", "forecast": ""}, {"time": "2022-06-15 23:50:00", "unixtime": 1655337000.0, "country": "JPY", "impact": "low", "event": "Imports (YoY) (May)", "forecast": "43.6%"}, {"time": "2022-06-15 23:50:00", "unixtime": 1655337000.0, "country": "JPY", "impact": "medium", "event": "Trade Balance (May)", "forecast": "-2,022.6B"}, {"time": "2022-06-16 01:00:00", "unixtime": 1655341200.0, "country": "AUD", "impact": "low", "event": "MI Inflation Expectations", "forecast": ""}, {"time": "2022-06-16 01:30:00", "unixtime": 1655343000.0, "country": "AUD", "impact": "high", "event": "Employment Change (May)", "forecast": "25.0K"}, {"time": "2022-06-16 01:30:00", "unixtime": 1655343000.0, "country": "AUD", "impact": "medium", "event": "Full Employment Change (May)", "forecast": ""}, {"time": "2022-06-16 01:30:00", "unixtime": 1655343000.0, "country": "AUD", "impact": "medium", "event": "House Price Index (QoQ) (Q1)", "forecast": "1.4%"}, {"time": "2022-06-16 01:30:00", "unixtime": 1655343000.0, "country": "AUD", "impact": "low", "event": "Participation Rate (May)", "forecast": "66.4%"}, {"time": "2022-06-16 01:30:00", "unixtime": 1655343000.0, "country": "AUD", "impact": "low", "event": "RBA Bulletin", "forecast": ""}, {"time": "2022-06-16 01:30:00", "unixtime": 1655343000.0, "country": "AUD", "impact": "medium", "event": "Unemployment Rate (May)", "forecast": "3.8%"}, {"time": "2022-06-16 01:30:00", "unixtime": 1655343000.0, "country": "CNY", "impact": "low", "event": "House Prices (YoY) (May)", "forecast": ""}, {"time": "2022-06-16 06:00:00", "unixtime": 1655359200.0, "country": "GBP", "impact": "low", "event": "Car Registration (MoM) (May)", "forecast": ""}, {"time": "2022-06-16 06:00:00", "unixtime": 1655359200.0, "country": "GBP", "impact": "low", "event": "Car Registration (YoY) (May)", "forecast": ""}, {"time": "2022-06-16 06:00:00", "unixtime": 1655359200.0, "country": "EUR", "impact": "low", "event": "Italian Car Registration (MoM) (May)", "forecast": ""}, {"time": "2022-06-16 06:00:00", "unixtime": 1655359200.0, "country": "EUR", "impact": "low", "event": "Italian Car Registration (YoY) (May)", "forecast": ""}, {"time": "2022-06-16 06:00:00", "unixtime": 1655359200.0, "country": "EUR", "impact": "low", "event": "German Car Registration (YoY) (May)", "forecast": ""}, {"time": "2022-06-16 06:00:00", "unixtime": 1655359200.0, "country": "EUR", "impact": "low", "event": "German Car Registration (MoM) (May)", "forecast": ""}, {"time": "2022-06-16 06:00:00", "unixtime": 1655359200.0, "country": "EUR", "impact": "low", "event": "French Car Registration (MoM) (May)", "forecast": ""}, {"time": "2022-06-16 06:00:00", "unixtime": 1655359200.0, "country": "EUR", "impact": "low", "event": "French Car Registration (YoY) (May)", "forecast": ""}, {"time": "2022-06-16 07:30:00", "unixtime": 1655364600.0, "country": "CHF", "impact": "high", "event": "SNB Interest Rate Decision (Q2)", "forecast": "-0.75%"}, {"time": "2022-06-16 07:30:00", "unixtime": 1655364600.0, "country": "CHF", "impact": "high", "event": "SNB Monetary Policy Assessment", "forecast": ""}, {"time": "2022-06-16 07:50:00", "unixtime": 1655365800.0, "country": "EUR", "impact": "medium", "event": "ECB's Panetta Speaks", "forecast": ""}, {"time": "2022-06-16 08:00:00", "unixtime": 1655366400.0, "country": "EUR", "impact": "low", "event": "Italian CPI (YoY) (May)", "forecast": "6.9%"}, {"time": "2022-06-16 08:00:00", "unixtime": 1655366400.0, "country": "EUR", "impact": "medium", "event": "Italian CPI (MoM) (May)", "forecast": "0.9%"}, {"time": "2022-06-16 08:00:00", "unixtime": 1655366400.0, "country": "EUR", "impact": "low", "event": "Italian CPI Ex Tobacco (MoM) (May)", "forecast": ""}, {"time": "2022-06-16 08:00:00", "unixtime": 1655366400.0, "country": "EUR", "impact": "low", "event": "Italian HICP (YoY) (May)", "forecast": "7.3%"}, {"time": "2022-06-16 08:00:00", "unixtime": 1655366400.0, "country": "EUR", "impact": "low", "event": "Italian HICP (MoM) (May)", "forecast": "0.9%"}, {"time": "2022-06-16 08:00:00", "unixtime": 1655366400.0, "country": "CHF", "impact": "high", "event": "SNB Press Conference", "forecast": ""}, {"time": "2022-06-16 08:00:00", "unixtime": 1655366400.0, "country": "EUR", "impact": "low", "event": "Spanish Trade Balance", "forecast": ""}, {"time": "2022-06-16 08:30:00", "unixtime": 1655368200.0, "country": "EUR", "impact": "medium", "event": "ECB's De Guindos Speaks", "forecast": ""}, {"time": "2022-06-16 09:00:00", "unixtime": 1655370000.0, "country": "EUR", "impact": "medium", "event": "German Buba Wuermeling Speaks", "forecast": ""}, {"time": "2022-06-16 09:00:00", "unixtime": 1655370000.0, "country": "EUR", "impact": "low", "event": "French 3-Year BTAN Auction", "forecast": ""}, {"time": "2022-06-16 09:00:00", "unixtime": 1655370000.0, "country": "EUR", "impact": "low", "event": "French 5-Year BTAN Auction", "forecast": ""}, {"time": "2022-06-16 09:00:00", "unixtime": 1655370000.0, "country": "EUR", "impact": "medium", "event": "Wages in euro zone (YoY) (Q1)", "forecast": ""}, {"time": "2022-06-16 09:00:00", "unixtime": 1655370000.0, "country": "EUR", "impact": "low", "event": "Labor Cost Index (YoY) (Q1)", "forecast": ""}, {"time": "2022-06-16 10:00:00", "unixtime": 1655373600.0, "country": "EUR", "impact": "medium", "event": "Eurogroup Meetings", "forecast": ""}, {"time": "2022-06-16 11:00:00", "unixtime": 1655377200.0, "country": "GBP", "impact": "medium", "event": "BoE MPC vote cut (Jun)", "forecast": "0"}, {"time": "2022-06-16 11:00:00", "unixtime": 1655377200.0, "country": "GBP", "impact": "medium", "event": "BoE MPC vote hike (Jun)", "forecast": "9"}, {"time": "2022-06-16 11:00:00", "unixtime": 1655377200.0, "country": "GBP", "impact": "medium", "event": "BoE MPC vote unchanged (Jun)", "forecast": "1"}, {"time": "2022-06-16 11:00:00", "unixtime": 1655377200.0, "country": "GBP", "impact": "medium", "event": "BoE QE Total (Jun)", "forecast": "875B"}, {"time": "2022-06-16 11:00:00", "unixtime": 1655377200.0, "country": "GBP", "impact": "high", "event": "BoE Interest Rate Decision (Jun)", "forecast": "1.25%"}, {"time": "2022-06-16 11:00:00", "unixtime": 1655377200.0, "country": "GBP", "impact": "high", "event": "BoE MPC Meeting Minutes", "forecast": ""}, {"time": "2022-06-16 12:30:00", "unixtime": 1655382600.0, "country": "USD", "impact": "high", "event": "Building Permits (May)", "forecast": "1.785M"}, {"time": "2022-06-16 12:30:00", "unixtime": 1655382600.0, "country": "USD", "impact": "medium", "event": "Building Permits (MoM) (May)", "forecast": ""}, {"time": "2022-06-16 12:30:00", "unixtime": 1655382600.0, "country": "USD", "impact": "low", "event": "Continuing Jobless Claims", "forecast": "1,302K"}, {"time": "2022-06-16 12:30:00", "unixtime": 1655382600.0, "country": "USD", "impact": "medium", "event": "Housing Starts (MoM) (May)", "forecast": ""}, {"time": "2022-06-16 12:30:00", "unixtime": 1655382600.0, "country": "USD", "impact": "medium", "event": "Housing Starts (May)", "forecast": "1.701M"}, {"time": "2022-06-16 12:30:00", "unixtime": 1655382600.0, "country": "USD", "impact": "high", "event": "Initial Jobless Claims", "forecast": "215K"}, {"time": "2022-06-16 12:30:00", "unixtime": 1655382600.0, "country": "USD", "impact": "low", "event": "Jobless Claims 4-Week Avg.", "forecast": ""}, {"time": "2022-06-16 12:30:00", "unixtime": 1655382600.0, "country": "USD", "impact": "high", "event": "Philadelphia Fed Manufacturing Index (Jun)", "forecast": "5.5"}, {"time": "2022-06-16 12:30:00", "unixtime": 1655382600.0, "country": "USD", "impact": "low", "event": "Philly Fed Business Conditions (Jun)", "forecast": ""}, {"time": "2022-06-16 12:30:00", "unixtime": 1655382600.0, "country": "USD", "impact": "low", "event": "Philly Fed CAPEX Index (Jun)", "forecast": ""}, {"time": "2022-06-16 12:30:00", "unixtime": 1655382600.0, "country": "USD", "impact": "medium", "event": "Philly Fed Employment (Jun)", "forecast": ""}, {"time": "2022-06-16 12:30:00", "unixtime": 1655382600.0, "country": "USD", "impact": "low", "event": "Philly Fed New Orders (Jun)", "forecast": ""}, {"time": "2022-06-16 12:30:00", "unixtime": 1655382600.0, "country": "USD", "impact": "low", "event": "Philly Fed Prices Paid (Jun)", "forecast": ""}, {"time": "2022-06-16 12:30:00", "unixtime": 1655382600.0, "country": "CAD", "impact": "medium", "event": "Wholesale Sales (MoM) (Apr)", "forecast": "0.2%"}, {"time": "2022-06-16 14:30:00", "unixtime": 1655389800.0, "country": "USD", "impact": "low", "event": "Natural Gas Storage", "forecast": "96B"}, {"time": "2022-06-16 15:30:00", "unixtime": 1655393400.0, "country": "USD", "impact": "low", "event": "4-Week Bill Auction", "forecast": ""}, {"time": "2022-06-16 15:30:00", "unixtime": 1655393400.0, "country": "USD", "impact": "low", "event": "8-Week Bill Auction", "forecast": ""}, {"time": "2022-06-16 17:00:00", "unixtime": 1655398800.0, "country": "EUR", "impact": "medium", "event": "German Buba Wuermeling Speaks", "forecast": ""}, {"time": "2022-06-16 22:30:00", "unixtime": 1655418600.0, "country": "NZD", "impact": "medium", "event": "Business NZ PMI (May)", "forecast": ""}, {"time": "2022-06-17 00:30:00", "unixtime": 1655425800.0, "country": "SGD", "impact": "low", "event": "Non-Oil Exports (MoM) (May)", "forecast": "1.40%"}, {"time": "2022-06-17 00:30:00", "unixtime": 1655425800.0, "country": "SGD", "impact": "low", "event": "Non-Oil Exports (YoY) (May)", "forecast": "7.60%"}, {"time": "2022-06-17 01:30:00", "unixtime": 1655429400.0, "country": "SGD", "impact": "low", "event": "Trade Balance", "forecast": ""}, {"time": "2022-06-17 03:00:00", "unixtime": 1655434800.0, "country": "JPY", "impact": "high", "event": "BoJ Monetary Policy Statement", "forecast": ""}, {"time": "2022-06-17 03:00:00", "unixtime": 1655434800.0, "country": "NZD", "impact": "low", "event": "RBNZ Offshore Holdings (May)", "forecast": ""}, {"time": "2022-06-17 04:00:00", "unixtime": 1655438400.0, "country": "IDR", "impact": "low", "event": "Motorbike Sales (YoY)", "forecast": ""}, {"time": "2022-06-17 08:00:00", "unixtime": 1655452800.0, "country": "EUR", "impact": "low", "event": "Italian Trade Balance Non-EU (Apr)", "forecast": ""}, {"time": "2022-06-17 08:00:00", "unixtime": 1655452800.0, "country": "JPY", "impact": "high", "event": "BoJ Press Conference", "forecast": ""}, {"time": "2022-06-17 08:30:00", "unixtime": 1655454600.0, "country": "GBP", "impact": "medium", "event": "BoE MPC Member Pill Speaks", "forecast": ""}, {"time": "2022-06-17 08:30:00", "unixtime": 1655454600.0, "country": "GBP", "impact": "medium", "event": "MPC Member Tenreyro Speaks", "forecast": ""}, {"time": "2022-06-17 08:30:00", "unixtime": 1655454600.0, "country": "HKD", "impact": "low", "event": "Unemployment Rate (May)", "forecast": ""}, {"time": "2022-06-17 09:00:00", "unixtime": 1655456400.0, "country": "EUR", "impact": "low", "event": "Italian Trade Balance (Apr)", "forecast": ""}, {"time": "2022-06-17 09:00:00", "unixtime": 1655456400.0, "country": "EUR", "impact": "low", "event": "Italian Trade Balance EU (Apr)", "forecast": ""}, {"time": "2022-06-17 09:00:00", "unixtime": 1655456400.0, "country": "EUR", "impact": "medium", "event": "Core CPI (YoY) (May)", "forecast": "3.8%"}, {"time": "2022-06-17 09:00:00", "unixtime": 1655456400.0, "country": "EUR", "impact": "low", "event": "Core CPI (MoM) (May)", "forecast": "0.5%"}, {"time": "2022-06-17 09:00:00", "unixtime": 1655456400.0, "country": "EUR", "impact": "medium", "event": "CPI (MoM) (May)", "forecast": "0.8%"}, {"time": "2022-06-17 09:00:00", "unixtime": 1655456400.0, "country": "EUR", "impact": "high", "event": "CPI (YoY) (May)", "forecast": "8.1%"}, {"time": "2022-06-17 09:00:00", "unixtime": 1655456400.0, "country": "EUR", "impact": "low", "event": "CPI ex Tobacco (MoM) (May)", "forecast": ""}, {"time": "2022-06-17 09:00:00", "unixtime": 1655456400.0, "country": "EUR", "impact": "low", "event": "CPI ex Tobacco (YoY) (May)", "forecast": ""}, {"time": "2022-06-17 09:00:00", "unixtime": 1655456400.0, "country": "EUR", "impact": "low", "event": "HICP ex Energy & Food (YoY) (May)", "forecast": "4.4%"}, {"time": "2022-06-17 09:00:00", "unixtime": 1655456400.0, "country": "EUR", "impact": "low", "event": "HICP ex Energy and Food (MoM) (May)", "forecast": "0.7%"}, {"time": "2022-06-17 11:00:00", "unixtime": 1655463600.0, "country": "GBP", "impact": "low", "event": "BoE Quarterly Bulletin", "forecast": ""}, {"time": "2022-06-17 11:30:00", "unixtime": 1655465400.0, "country": "INR", "impact": "low", "event": "Bank Loan Growth", "forecast": ""}, {"time": "2022-06-17 11:30:00", "unixtime": 1655465400.0, "country": "INR", "impact": "low", "event": "Deposit Growth", "forecast": ""}, {"time": "2022-06-17 11:30:00", "unixtime": 1655465400.0, "country": "INR", "impact": "low", "event": "FX Reserves, USD", "forecast": ""}, {"time": "2022-06-17 11:30:00", "unixtime": 1655465400.0, "country": "INR", "impact": "low", "event": "FX Reserves, USD", "forecast": ""}, {"time": "2022-06-17 12:30:00", "unixtime": 1655469000.0, "country": "CAD", "impact": "medium", "event": "Foreign Securities Purchases (Apr)", "forecast": ""}, {"time": "2022-06-17 12:30:00", "unixtime": 1655469000.0, "country": "CAD", "impact": "low", "event": "Foreign Securities Purchases by Canadians (Apr)", "forecast": ""}, {"time": "2022-06-17 12:30:00", "unixtime": 1655469000.0, "country": "CAD", "impact": "low", "event": "IPPI (YoY) (May)", "forecast": ""}, {"time": "2022-06-17 12:30:00", "unixtime": 1655469000.0, "country": "CAD", "impact": "low", "event": "IPPI (MoM) (May)", "forecast": "0.5%"}, {"time": "2022-06-17 12:30:00", "unixtime": 1655469000.0, "country": "CAD", "impact": "low", "event": "RMPI (YoY) (May)", "forecast": ""}, {"time": "2022-06-17 12:30:00", "unixtime": 1655469000.0, "country": "CAD", "impact": "medium", "event": "RMPI (MoM) (May)", "forecast": ""}, {"time": "2022-06-17 12:45:00", "unixtime": 1655469900.0, "country": "USD", "impact": "high", "event": "Fed Chair Powell Speaks", "forecast": ""}, {"time": "2022-06-17 13:15:00", "unixtime": 1655471700.0, "country": "USD", "impact": "low", "event": "Capacity Utilization Rate (May)", "forecast": "79.2%"}, {"time": "2022-06-17 13:15:00", "unixtime": 1655471700.0, "country": "USD", "impact": "medium", "event": "Industrial Production (YoY) (May)", "forecast": ""}, {"time": "2022-06-17 13:15:00", "unixtime": 1655471700.0, "country": "USD", "impact": "medium", "event": "Industrial Production (MoM) (May)", "forecast": "0.4%"}, {"time": "2022-06-17 13:15:00", "unixtime": 1655471700.0, "country": "USD", "impact": "low", "event": "Manufacturing Production (MoM) (May)", "forecast": "0.3%"}, {"time": "2022-06-17 14:00:00", "unixtime": 1655474400.0, "country": "USD", "impact": "low", "event": "US Leading Index (MoM) (May)", "forecast": "-0.4%"}, {"time": "2022-06-17 14:30:00", "unixtime": 1655476200.0, "country": "GBP", "impact": "medium", "event": "BoE MPC Member Pill Speaks", "forecast": ""}, {"time": "2022-06-17 16:40:00", "unixtime": 1655484000.0, "country": "JPY", "impact": "medium", "event": "BoJ Interest Rate Decision", "forecast": "-0.10%"}, {"time": "2022-06-17 17:00:00", "unixtime": 1655485200.0, "country": "USD", "impact": "medium", "event": "U.S. Baker Hughes Oil Rig Count", "forecast": ""}, {"time": "2022-06-17 17:00:00", "unixtime": 1655485200.0, "country": "USD", "impact": "medium", "event": "U.S. Baker Hughes Total Rig Count", "forecast": ""}, {"time": "2022-06-17 19:30:00", "unixtime": 1655494200.0, "country": "GBP", "impact": "medium", "event": "CFTC GBP speculative net positions", "forecast": ""}, {"time": "2022-06-17 19:30:00", "unixtime": 1655494200.0, "country": "USD", "impact": "low", "event": "CFTC Aluminium speculative net positions", "forecast": ""}, {"time": "2022-06-17 19:30:00", "unixtime": 1655494200.0, "country": "USD", "impact": "low", "event": "CFTC Copper speculative net positions", "forecast": ""}, {"time": "2022-06-17 19:30:00", "unixtime": 1655494200.0, "country": "USD", "impact": "low", "event": "CFTC Corn speculative net positions", "forecast": ""}, {"time": "2022-06-17 19:30:00", "unixtime": 1655494200.0, "country": "USD", "impact": "medium", "event": "CFTC Crude Oil speculative net positions", "forecast": ""}, {"time": "2022-06-17 19:30:00", "unixtime": 1655494200.0, "country": "USD", "impact": "medium", "event": "CFTC Gold speculative net positions", "forecast": ""}, {"time": "2022-06-17 19:30:00", "unixtime": 1655494200.0, "country": "USD", "impact": "medium", "event": "CFTC Nasdaq 100 speculative net positions", "forecast": ""}, {"time": "2022-06-17 19:30:00", "unixtime": 1655494200.0, "country": "USD", "impact": "low", "event": "CFTC Natural Gas speculative net positions", "forecast": ""}, {"time": "2022-06-17 19:30:00", "unixtime": 1655494200.0, "country": "USD", "impact": "medium", "event": "CFTC S&P 500 speculative net positions", "forecast": ""}, {"time": "2022-06-17 19:30:00", "unixtime": 1655494200.0, "country": "USD", "impact": "low", "event": "CFTC Silver speculative net positions", "forecast": ""}, {"time": "2022-06-17 19:30:00", "unixtime": 1655494200.0, "country": "USD", "impact": "low", "event": "CFTC Soybeans speculative net positions", "forecast": ""}, {"time": "2022-06-17 19:30:00", "unixtime": 1655494200.0, "country": "USD", "impact": "low", "event": "CFTC Wheat speculative net positions", "forecast": ""}, {"time": "2022-06-17 19:30:00", "unixtime": 1655494200.0, "country": "CAD", "impact": "low", "event": "CFTC CAD speculative net positions", "forecast": ""}, {"time": "2022-06-17 19:30:00", "unixtime": 1655494200.0, "country": "MXN", "impact": "low", "event": "CFTC MXN speculative net positions", "forecast": ""}, {"time": "2022-06-17 19:30:00", "unixtime": 1655494200.0, "country": "CHF", "impact": "low", "event": "CFTC CHF speculative net positions", "forecast": ""}, {"time": "2022-06-17 19:30:00", "unixtime": 1655494200.0, "country": "AUD", "impact": "medium", "event": "CFTC AUD speculative net positions", "forecast": ""}, {"time": "2022-06-17 19:30:00", "unixtime": 1655494200.0, "country": "BRL", "impact": "medium", "event": "CFTC BRL speculative net positions", "forecast": ""}, {"time": "2022-06-17 19:30:00", "unixtime": 1655494200.0, "country": "JPY", "impact": "medium", "event": "CFTC JPY speculative net positions", "forecast": ""}, {"time": "2022-06-17 19:30:00", "unixtime": 1655494200.0, "country": "NZD", "impact": "low", "event": "CFTC NZD speculative net positions", "forecast": ""}, {"time": "2022-06-17 19:30:00", "unixtime": 1655494200.0, "country": "EUR", "impact": "medium", "event": "CFTC EUR speculative net positions", "forecast": ""}, {"time": "2022-06-18 08:40:00", "unixtime": 1655541600.0, "country": "USD", "impact": "medium", "event": "Fed Waller Speaks", "forecast": ""}]}